README.rst
setup.py
sqlalchemy_multidb/__init__.py
sqlalchemy_multidb/databases.py
sqlalchemy_multidb/exceptions.py
sqlalchemy_multidb/sessions.py
sqlalchemy_multidb/util.py
sqlalchemy_multidb.egg-info/PKG-INFO
sqlalchemy_multidb.egg-info/SOURCES.txt
sqlalchemy_multidb.egg-info/dependency_links.txt
sqlalchemy_multidb.egg-info/requires.txt
sqlalchemy_multidb.egg-info/top_level.txt