Metadata-Version: 1.1
Name: sqlalchemy-multidb
Version: 0.8.2
Summary: Provides methods to load the database configurations from a config file and access multiple databases easily.
Home-page: https://github.com/viniciuschiele/sqlalchemy-multidb
Author: Vinicius Chiele
Author-email: vinicius.chiele@gmail.com
License: Apache 2.0
Keywords: sqlalchemy
Platform: UNKNOWN
Classifier: Development Status :: 5 - Production/Stable
Classifier: Intended Audience :: Developers
Classifier: Natural Language :: English
Classifier: Operating System :: OS Independent
Classifier: Programming Language :: Python :: 3
Classifier: Programming Language :: Python :: 3.2
Classifier: Programming Language :: Python :: 3.3
Classifier: Programming Language :: Python :: 3.4
Classifier: Programming Language :: Python :: Implementation :: CPython
Classifier: Topic :: Software Development :: Libraries
Classifier: Topic :: Software Development :: Libraries :: Python Modules
